radcam/perturber.py
radcam/radcam.py
radcam-1.0.0.dist-info/WHEEL
radcam-1.0.0.dist-info/METADATA
radcam-1.0.0.dist-info/RECORD
